{
 "actions": [],
 "allow_rename": 1,
 "autoname": "field:email",
 "creation": "2024-10-29 20:02:48.221453",
 "doctype": "DocType",
 "editable_grid": 1,
 "engine": "InnoDB",
 "field_order": [
  "email",
  "is_primary"
 ],
 "fields": [
  {
   "fieldname": "email",
   "fieldtype": "Data",
   "in_list_view": 1,
   "label": "Email",
   "reqd": 1,
   "unique": 1
  },
  {
   "default": "0",
   "fieldname": "is_primary",
   "fieldtype": "Check",
   "label": "Is Primary"
  }
 ],
 "index_web_pages_for_search": 1,
 "istable": 1,
 "links": [],
 "modified": "2024-10-29 20:22:00.520350",
 "modified_by": "Administrator",
 "module": "Assignments",
 "name": "Customer Email",
 "naming_rule": "By fieldname",
 "owner": "Administrator",
 "permissions": [],
 "sort_field": "modified",
 "sort_order": "DESC",
 "states": [],
 "track_changes": 1
}